{
  "name": "new-feature",
  "statuses": [
    {
      "id": "implemented",
      "name": "Implemented",
      "color": "#10B981"
    },
    {
      "id": "intended",
      "name": "Intended",
      "color": "#3B82F6"
    },
    {
      "id": "aspirational",
      "name": "Aspirational",
      "color": "#A855F7"
    }
  ],
  "featureProjects": [
    {
      "id": "foundation-1770317169043",
      "name": "Foundation",
      "color": "#c70000"
    },
    {
      "id": "digitalplaybook-1770319806139",
      "name": "DigitalPlaybook",
      "color": "#38bdf8"
    }
  ],
  "nodes": [
    {
      "id": "86d301959835892d",
      "label": "Feature 1",
      "name": "Feature 1",
      "statusId": "implemented",
      "projectId": "foundation-1770317169043",
      "notes": "",
      "tags": [
        "API",
        "DOC"
      ],
      "attributes": [
        {
          "key": "test",
          "value": "test"
        }
      ],
      "position": {
        "x": -314.0,
        "y": -69.0
      }
    },
    {
      "id": "dd1896339eec9113",
      "label": "Feature 2",
      "name": "Feature 2",
      "statusId": "implemented",
      "projectId": "foundation-1770317169043",
      "notes": "",
      "tags": [],
      "attributes": [
        {
          "key": "test",
          "value": "test"
        }
      ],
      "position": {
        "x": 257.0,
        "y": 87.0
      }
    },
    {
      "id": "e1a7be39e5aa7e3f",
      "label": "Feature 3",
      "name": "Feature 3",
      "statusId": "aspirational",
      "projectId": "digitalplaybook-1770319806139",
      "notes": "",
      "tags": [
        "API",
        "DOC",
        "Test"
      ],
      "attributes": [],
      "position": {
        "x": 486.0,
        "y": 11.0
      }
    }
  ],
  "connections": [
    {
      "id": "d73b746479f4657d",
      "sourceId": "dd1896339eec9113",
      "sourceOutput": "out",
      "targetId": "e1a7be39e5aa7e3f",
      "targetInput": "in",
      "pins": []
    },
    {
      "id": "9c222608363b67d3",
      "sourceId": "86d301959835892d",
      "sourceOutput": "out",
      "targetId": "dd1896339eec9113",
      "targetInput": "in",
      "pins": []
    }
  ]
}